PyEncrypter/__init__.py
PyEncrypter/script.py
PyEncrypter-0.2.3.dist-info/LICENSE
PyEncrypter-0.2.3.dist-info/METADATA
PyEncrypter-0.2.3.dist-info/WHEEL
PyEncrypter-0.2.3.dist-info/top_level.txt
PyEncrypter-0.2.3.dist-info/RECORD
