Metadata-Version: 2.1
Name: PyEncrypter
Version: 0.2.3
Summary: A simple yet secure encryption package.
Home-page: https://github.com/G8MR/PyEncrypter/
Author: G8MR
Classifier: Programming Language :: Python :: 3
Classifier: License :: OSI Approved :: MIT License
Classifier: Operating System :: OS Independent
Requires-Python: >=3.6
License-File: LICENSE
